mesh2sdf/__init__.py
mesh2sdf/compute.py
mesh2sdf/core.cp38-win_amd64.pyd
mesh2sdf-1.1.0.dist-info/METADATA
mesh2sdf-1.1.0.dist-info/WHEEL
mesh2sdf-1.1.0.dist-info/top_level.txt
mesh2sdf-1.1.0.dist-info/RECORD
