Metadata-Version: 2.1
Name: mesh2sdf
Version: 1.1.0
Summary: Compute the signed distance field from an input mesh
Home-page: https://github.com/wang-ps/mesh2sdf
Author: Peng-Shuai Wang
Author-email: wangps@hotmail.com
Classifier: Programming Language :: Python :: 3
Classifier: License :: OSI Approved :: MIT License
Classifier: Operating System :: OS Independent
Requires-Python: >=3.6
Requires-Dist: numpy
Requires-Dist: trimesh
Requires-Dist: scikit-image
